comram/__init__.py
comram/dmsg.py
comram/procon.py
comram/ramshare.py
comram-0.0.12.dist-info/LICENSE
comram-0.0.12.dist-info/METADATA
comram-0.0.12.dist-info/WHEEL
comram-0.0.12.dist-info/top_level.txt
comram-0.0.12.dist-info/RECORD
