Metadata-Version: 2.1
Name: comram
Version: 0.0.12
Summary: shared ram based data distribution lib
Home-page: https://github.com/mKunzendorf/comram
Author: Mikael Kunzendorf Nissen
Author-email: mmkunzendorf@gmail.com
License: UNKNOWN
Project-URL: Bug Tracker, https://github.com/mKunzendorf/comram/issues
Platform: UNKNOWN
Classifier: Programming Language :: Python :: 3
Classifier: License :: OSI Approved :: MIT License
Classifier: Operating System :: POSIX :: Linux
Requires-Python: >=3.6
License-File: LICENSE
